{
    "Parameter": "Littoral AAbundance",
    "Location": "VVL_My Thuan_Vinh Long",
    "Station Code": "019812",
    "Unit": "Species Count",
    "Data": [
        {
            "Time": "2011-12-30T17:00Z",
            "Value": "83.0"
        },
        {
            "Time": "2013-12-30T17:00Z",
            "Value": "12.0"
        },
        {
            "Time": "2015-12-30T17:00Z",
            "Value": "22.0"
        },
        {
            "Time": "2017-12-30T17:00Z",
            "Value": "92.0"
        },
        {
            "Time": "2019-12-30T17:00Z",
            "Value": "82.0"
        },
        {
            "Time": "2021-12-30T17:00Z",
            "Value": "20.0"
        }
    ]
}